spin_stepper/__init__.py
spin_stepper/spin_chain.py
spin_stepper/spin_device.py
spin_stepper-0.0.8.dist-info/licenses/LICENSE
spin_stepper-0.0.8.dist-info/METADATA
spin_stepper-0.0.8.dist-info/WHEEL
spin_stepper-0.0.8.dist-info/top_level.txt
spin_stepper-0.0.8.dist-info/RECORD
