Metadata-Version: 2.4
Name: spin_stepper
Version: 0.0.8
Summary: Python interface for stepper motor drivers from the STMicroelectronics STSPIN family (L6470).
Author-email: Ulrik Södergren <ulrik.sodergren@luxbright.com>
Maintainer-email: Ulrik Södergren <ulrik.sodergren@luxbright.com>
Project-URL: Homepage, https://github.com/luxbright-com/spin_stepper
Keywords: L6470,L6470HTR,STSPIN,STMicroelectronics,Stepper Motor,Raspberry Pi,SPI
Classifier: Development Status :: 3 - Alpha
Classifier: Programming Language :: Python :: 3
Classifier: License :: OSI Approved :: MIT License
Requires-Python: >=3.11
License-File: LICENSE
Requires-Dist: spidev
Provides-Extra: tests
Requires-Dist: pytest>8.0; extra == "tests"
Requires-Dist: pytest-timeout>2.3; extra == "tests"
Provides-Extra: dev
Requires-Dist: ruff; extra == "dev"
Dynamic: license-file
